LICENSE
README.md
parallely/__init__.py
parallely/base.py
parallely/coroutines.py
parallely/processes.py
parallely/threads.py
parallely/utils.py
parallely-0.2.6.dist-info/LICENSE
parallely-0.2.6.dist-info/WHEEL
parallely-0.2.6.dist-info/METADATA
parallely-0.2.6.dist-info/RECORD
