Metadata-Version: 2.1
Name: parallely
Version: 0.2.6
Summary: The simplest way to utilize multiple threads, processes, and async functions in Python
License: Apache-2.0
Author: Mikkel Vilstrup
Author-email: mikkel@vilstrup.dk
Requires-Python: >=3.7,<3.11
Classifier: Environment :: Console
Classifier: Intended Audience :: Developers
Classifier: License :: OSI Approved :: Apache Software License
Classifier: Natural Language :: English
Classifier: Operating System :: OS Independent
Classifier: Programming Language :: Python :: 3
Classifier: Programming Language :: Python :: 3.7
Classifier: Programming Language :: Python :: 3.8
Classifier: Programming Language :: Python :: 3.9
Classifier: Topic :: Software Development :: Libraries
Requires-Dist: asyncio (>=3.4.3,<4.0.0)
Requires-Dist: nest-asyncio (>=1.5.1,<2.0.0)
Requires-Dist: pathos (>=0.2.8,<0.3.0)
